{
    "Consumer Price Index (CPI)": {
        "Construction URL": "http://dataservices.imf.org/REST/SDMX_JSON.svc/CompactData/<DatabaseID>/<Frequency>.<RegionCode>.<IndicatorKey>?startPeriod=<StartDate>&endPeriod=<EndDate>",
        "Sample URL": "http://dataservices.imf.org/REST/SDMX_JSON.svc/CompactData/CPI/A.FR",
        "Sample URL Description": "Returns all the CPI indicators for France at annual frequency.",
        "Frequencies": [
            {
                "Frequency Key": "A",
                "Frequency Name": "Annual"
            },
            {
                "Frequency Key": "B",
                "Frequency Name": "Bi-annual"
            },
            {
                "Frequency Key": "Q",
                "Frequency Name": "Quarterly"
            },
            {
                "Frequency Key": "M",
                "Frequency Name": "Monthly"
            },
            {
                "Frequency Key": "D",
                "Frequency Name": "Daily"
            },
            {
                "Frequency Key": "W",
                "Frequency Name": "Weekly"
            }
        ],
        "Regions": [
            {
                "Region Key": "AF",
                "Region Name": "Afghanistan"
            },
            {
                "Region Key": "AL",
                "Region Name": "Albania"
            },
            {
                "Region Key": "DZ",
                "Region Name": "Algeria"
            },
            {
                "Region Key": "AS",
                "Region Name": "American Samoa"
            },
            {
                "Region Key": "AD",
                "Region Name": "Andorra"
            },
            {
                "Region Key": "AO",
                "Region Name": "Angola"
            },
            {
                "Region Key": "AI",
                "Region Name": "Anguilla"
            },
            {
                "Region Key": "AG",
                "Region Name": "Antigua and Barbuda"
            },
            {
                "Region Key": "AR",
                "Region Name": "Argentina"
            },
            {
                "Region Key": "AM",
                "Region Name": "Armenia"
            },
            {
                "Region Key": "AW",
                "Region Name": "Aruba"
            },
            {
                "Region Key": "AU",
                "Region Name": "Australia"
            },
            {
                "Region Key": "AT",
                "Region Name": "Austria"
            },
            {
                "Region Key": "AZ",
                "Region Name": "Azerbaijan"
            },
            {
                "Region Key": "BS",
                "Region Name": "Bahamas"
            },
            {
                "Region Key": "BH",
                "Region Name": "Bahrain"
            },
            {
                "Region Key": "BD",
                "Region Name": "Bangladesh"
            },
            {
                "Region Key": "BB",
                "Region Name": "Barbados"
            },
            {
                "Region Key": "BY",
                "Region Name": "Belarus"
            },
            {
                "Region Key": "BE",
                "Region Name": "Belgium"
            },
            {
                "Region Key": "BZ",
                "Region Name": "Belize"
            },
            {
                "Region Key": "BJ",
                "Region Name": "Benin"
            },
            {
                "Region Key": "BM",
                "Region Name": "Bermuda"
            },
            {
                "Region Key": "BT",
                "Region Name": "Bhutan"
            },
            {
                "Region Key": "BO",
                "Region Name": "Bolivia"
            },
            {
                "Region Key": "BA",
                "Region Name": "Bosnia and Herzegovina"
            },
            {
                "Region Key": "BW",
                "Region Name": "Botswana"
            },
            {
                "Region Key": "BV",
                "Region Name": "Bouvet Island"
            },
            {
                "Region Key": "BR",
                "Region Name": "Brazil"
            },
            {
                "Region Key": "IO",
                "Region Name": "British Indian Ocean territory"
            },
            {
                "Region Key": "BN",
                "Region Name": "Brunei Darussalam"
            },
            {
                "Region Key": "BG",
                "Region Name": "Bulgaria"
            },
            {
                "Region Key": "BF",
                "Region Name": "Burkina Faso"
            },
            {
                "Region Key": "BI",
                "Region Name": "Burundi"
            },
            {
                "Region Key": "CV",
                "Region Name": "Cabo Verde"
            },
            {
                "Region Key": "KH",
                "Region Name": "Cambodia"
            },
            {
                "Region Key": "CM",
                "Region Name": "Cameroon"
            },
            {
                "Region Key": "CA",
                "Region Name": "Canada"
            },
            {
                "Region Key": "KY",
                "Region Name": "Cayman Islands"
            },
            {
                "Region Key": "CF",
                "Region Name": "Central African Republic"
            },
            {
                "Region Key": "TD",
                "Region Name": "Chad"
            },
            {
                "Region Key": "CL",
                "Region Name": "Chile"
            },
            {
                "Region Key": "HK",
                "Region Name": "Hong Kong"
            },
            {
                "Region Key": "MO",
                "Region Name": "Macao"
            },
            {
                "Region Key": "CN",
                "Region Name": "China"
            },
            {
                "Region Key": "CO",
                "Region Name": "Colombia"
            },
            {
                "Region Key": "KM",
                "Region Name": "Comoros"
            },
            {
                "Region Key": "CD",
                "Region Name": "Congo, the Democratic Republic of the"
            },
            {
                "Region Key": "CG",
                "Region Name": "Congo"
            },
            {
                "Region Key": "CK",
                "Region Name": "Cook Islands"
            },
            {
                "Region Key": "CR",
                "Region Name": "Costa Rica"
            },
            {
                "Region Key": "CI",
                "Region Name": "Cote d`Ivoire"
            },
            {
                "Region Key": "HR",
                "Region Name": "Croatia"
            },
            {
                "Region Key": "CU",
                "Region Name": "Cuba"
            },
            {
                "Region Key": "CW",
                "Region Name": "Curacao"
            },
            {
                "Region Key": "CY",
                "Region Name": "Cyprus"
            },
            {
                "Region Key": "CZ",
                "Region Name": "Czech Republic"
            },
            {
                "Region Key": "DK",
                "Region Name": "Denmark"
            },
            {
                "Region Key": "DJ",
                "Region Name": "Djibouti"
            },
            {
                "Region Key": "DM",
                "Region Name": "Dominica"
            },
            {
                "Region Key": "DO",
                "Region Name": "Dominican Republic"
            },
            {
                "Region Key": "EC",
                "Region Name": "Ecuador"
            },
            {
                "Region Key": "EG",
                "Region Name": "Egypt"
            },
            {
                "Region Key": "SV",
                "Region Name": "El Salvador"
            },
            {
                "Region Key": "GQ",
                "Region Name": "Equatorial Guinea"
            },
            {
                "Region Key": "ER",
                "Region Name": "Eritrea"
            },
            {
                "Region Key": "EE",
                "Region Name": "Estonia"
            },
            {
                "Region Key": "ET",
                "Region Name": "Ethiopia"
            },
            {
                "Region Key": "FK",
                "Region Name": "Falkland Islands (Malvinas)"
            },
            {
                "Region Key": "FO",
                "Region Name": "Faroe Islands"
            },
            {
                "Region Key": "FJ",
                "Region Name": "Fiji"
            },
            {
                "Region Key": "FI",
                "Region Name": "Finland"
            },
            {
                "Region Key": "FR",
                "Region Name": "France"
            },
            {
                "Region Key": "TF",
                "Region Name": "French Southern Territories"
            },
            {
                "Region Key": "PF",
                "Region Name": "French Polynesia"
            },
            {
                "Region Key": "NC",
                "Region Name": "New Caledonia"
            },
            {
                "Region Key": "GA",
                "Region Name": "Gabon"
            },
            {
                "Region Key": "GM",
                "Region Name": "Gambia"
            },
            {
                "Region Key": "GE",
                "Region Name": "Georgia"
            },
            {
                "Region Key": "DE",
                "Region Name": "Germany"
            },
            {
                "Region Key": "GH",
                "Region Name": "Ghana"
            },
            {
                "Region Key": "GI",
                "Region Name": "Gibraltar"
            },
            {
                "Region Key": "GR",
                "Region Name": "Greece"
            },
            {
                "Region Key": "GL",
                "Region Name": "Greenland"
            },
            {
                "Region Key": "GD",
                "Region Name": "Grenada"
            },
            {
                "Region Key": "GP",
                "Region Name": "Guadeloupe"
            },
            {
                "Region Key": "GU",
                "Region Name": "Guam"
            },
            {
                "Region Key": "GT",
                "Region Name": "Guatemala"
            },
            {
                "Region Key": "GG",
                "Region Name": "Guernsey"
            },
            {
                "Region Key": "GF",
                "Region Name": "French Guiana"
            },
            {
                "Region Key": "GN",
                "Region Name": "Guinea"
            },
            {
                "Region Key": "GW",
                "Region Name": "Guinea-Bissau"
            },
            {
                "Region Key": "GY",
                "Region Name": "Guyana"
            },
            {
                "Region Key": "HT",
                "Region Name": "Haiti"
            },
            {
                "Region Key": "HN",
                "Region Name": "Honduras"
            },
            {
                "Region Key": "HU",
                "Region Name": "Hungary"
            },
            {
                "Region Key": "IS",
                "Region Name": "Iceland"
            },
            {
                "Region Key": "IN",
                "Region Name": "India"
            },
            {
                "Region Key": "ID",
                "Region Name": "Indonesia"
            },
            {
                "Region Key": "IR",
                "Region Name": "Iran, Islamic Republic of"
            },
            {
                "Region Key": "IQ",
                "Region Name": "Iraq"
            },
            {
                "Region Key": "IE",
                "Region Name": "Ireland"
            },
            {
                "Region Key": "IM",
                "Region Name": "Isle of Man"
            },
            {
                "Region Key": "IL",
                "Region Name": "Israel"
            },
            {
                "Region Key": "IT",
                "Region Name": "Italy"
            },
            {
                "Region Key": "JM",
                "Region Name": "Jamaica"
            },
            {
                "Region Key": "JP",
                "Region Name": "Japan"
            },
            {
                "Region Key": "JE",
                "Region Name": "Jersey"
            },
            {
                "Region Key": "JO",
                "Region Name": "Jordan"
            },
            {
                "Region Key": "KZ",
                "Region Name": "Kazakhstan"
            },
            {
                "Region Key": "KE",
                "Region Name": "Kenya"
            },
            {
                "Region Key": "KI",
                "Region Name": "Kiribati"
            },
            {
                "Region Key": "KR",
                "Region Name": "Korea, Republic of"
            },
            {
                "Region Key": "XK",
                "Region Name": "Kosovo, Republic of"
            },
            {
                "Region Key": "KW",
                "Region Name": "Kuwait"
            },
            {
                "Region Key": "KG",
                "Region Name": "Kyrgyzstan"
            },
            {
                "Region Key": "LA",
                "Region Name": "Lao People`s Democratic Republic"
            },
            {
                "Region Key": "LV",
                "Region Name": "Latvia"
            },
            {
                "Region Key": "LB",
                "Region Name": "Lebanon"
            },
            {
                "Region Key": "LS",
                "Region Name": "Lesotho"
            },
            {
                "Region Key": "LR",
                "Region Name": "Liberia"
            },
            {
                "Region Key": "LY",
                "Region Name": "Libya"
            },
            {
                "Region Key": "LI",
                "Region Name": "Liechtenstein"
            },
            {
                "Region Key": "LT",
                "Region Name": "Lithuania"
            },
            {
                "Region Key": "LU",
                "Region Name": "Luxembourg"
            },
            {
                "Region Key": "MK",
                "Region Name": "North Macedonia, Republic of"
            },
            {
                "Region Key": "MG",
                "Region Name": "Madagascar"
            },
            {
                "Region Key": "MW",
                "Region Name": "Malawi"
            },
            {
                "Region Key": "MY",
                "Region Name": "Malaysia"
            },
            {
                "Region Key": "MV",
                "Region Name": "Maldives"
            },
            {
                "Region Key": "ML",
                "Region Name": "Mali"
            },
            {
                "Region Key": "MT",
                "Region Name": "Malta"
            },
            {
                "Region Key": "MH",
                "Region Name": "Marshall islands"
            },
            {
                "Region Key": "MQ",
                "Region Name": "Martinique"
            },
            {
                "Region Key": "MR",
                "Region Name": "Mauritania"
            },
            {
                "Region Key": "MU",
                "Region Name": "Mauritius"
            },
            {
                "Region Key": "YT",
                "Region Name": "Mayotte"
            },
            {
                "Region Key": "MX",
                "Region Name": "Mexico"
            },
            {
                "Region Key": "FM",
                "Region Name": "Micronesia, Federated States of"
            },
            {
                "Region Key": "MD",
                "Region Name": "Moldova, Republic of"
            },
            {
                "Region Key": "MC",
                "Region Name": "Monaco"
            },
            {
                "Region Key": "MN",
                "Region Name": "Mongolia"
            },
            {
                "Region Key": "ME",
                "Region Name": "Montenegro"
            },
            {
                "Region Key": "MS",
                "Region Name": "Montserrat"
            },
            {
                "Region Key": "MA",
                "Region Name": "Morocco"
            },
            {
                "Region Key": "MZ",
                "Region Name": "Mozambique"
            },
            {
                "Region Key": "MM",
                "Region Name": "Myanmar"
            },
            {
                "Region Key": "NA",
                "Region Name": "Namibia"
            },
            {
                "Region Key": "NR",
                "Region Name": "Nauru"
            },
            {
                "Region Key": "NP",
                "Region Name": "Nepal"
            },
            {
                "Region Key": "NL",
                "Region Name": "Netherlands"
            },
            {
                "Region Key": "AN",
                "Region Name": "Netherlands Antilles"
            },
            {
                "Region Key": "NZ",
                "Region Name": "New Zealand"
            },
            {
                "Region Key": "NI",
                "Region Name": "Nicaragua"
            },
            {
                "Region Key": "NE",
                "Region Name": "Niger"
            },
            {
                "Region Key": "NG",
                "Region Name": "Nigeria"
            },
            {
                "Region Key": "NO",
                "Region Name": "Norway"
            },
            {
                "Region Key": "OM",
                "Region Name": "Oman"
            },
            {
                "Region Key": "PK",
                "Region Name": "Pakistan"
            },
            {
                "Region Key": "PW",
                "Region Name": "Palau"
            },
            {
                "Region Key": "PA",
                "Region Name": "Panama"
            },
            {
                "Region Key": "PG",
                "Region Name": "Papua New Guinea"
            },
            {
                "Region Key": "PY",
                "Region Name": "Paraguay"
            },
            {
                "Region Key": "PE",
                "Region Name": "Peru"
            },
            {
                "Region Key": "PH",
                "Region Name": "Philippines"
            },
            {
                "Region Key": "PL",
                "Region Name": "Poland"
            },
            {
                "Region Key": "PT",
                "Region Name": "Portugal"
            },
            {
                "Region Key": "QA",
                "Region Name": "Qatar"
            },
            {
                "Region Key": "RE",
                "Region Name": "Reunion"
            },
            {
                "Region Key": "RO",
                "Region Name": "Romania"
            },
            {
                "Region Key": "RU",
                "Region Name": "Russian Federation"
            },
            {
                "Region Key": "RW",
                "Region Name": "Rwanda"
            },
            {
                "Region Key": "SH",
                "Region Name": "Saint Helena"
            },
            {
                "Region Key": "PM",
                "Region Name": "Saint Pierre and Miquelon"
            },
            {
                "Region Key": "WS",
                "Region Name": "Samoa"
            },
            {
                "Region Key": "SM",
                "Region Name": "San Marino"
            },
            {
                "Region Key": "ST",
                "Region Name": "Sao Tome and Principe"
            },
            {
                "Region Key": "SA",
                "Region Name": "Saudi Arabia"
            },
            {
                "Region Key": "SN",
                "Region Name": "Senegal"
            },
            {
                "Region Key": "RS",
                "Region Name": "Serbia"
            },
            {
                "Region Key": "SC",
                "Region Name": "Seychelles"
            },
            {
                "Region Key": "SL",
                "Region Name": "Sierra Leone"
            },
            {
                "Region Key": "SG",
                "Region Name": "Singapore"
            },
            {
                "Region Key": "SX",
                "Region Name": "Sint Maarten (Dutch part)"
            },
            {
                "Region Key": "SK",
                "Region Name": "Slovakia"
            },
            {
                "Region Key": "SI",
                "Region Name": "Slovenia"
            },
            {
                "Region Key": "SB",
                "Region Name": "Solomon Islands"
            },
            {
                "Region Key": "SO",
                "Region Name": "Somalia"
            },
            {
                "Region Key": "ZA",
                "Region Name": "South Africa"
            },
            {
                "Region Key": "SS",
                "Region Name": "South Sudan"
            },
            {
                "Region Key": "ES",
                "Region Name": "Spain"
            },
            {
                "Region Key": "LK",
                "Region Name": "Sri Lanka"
            },
            {
                "Region Key": "KN",
                "Region Name": "Saint Kitts and Nevis"
            },
            {
                "Region Key": "LC",
                "Region Name": "Saint Lucia"
            },
            {
                "Region Key": "VC",
                "Region Name": "Saint Vincent and the Grenadines"
            },
            {
                "Region Key": "SD",
                "Region Name": "Sudan"
            },
            {
                "Region Key": "SR",
                "Region Name": "Suriname"
            },
            {
                "Region Key": "SZ",
                "Region Name": "Eswatini"
            },
            {
                "Region Key": "SE",
                "Region Name": "Sweden"
            },
            {
                "Region Key": "CH",
                "Region Name": "Switzerland"
            },
            {
                "Region Key": "SY",
                "Region Name": "Syrian Arab Republic"
            },
            {
                "Region Key": "TW",
                "Region Name": "Taiwan, Province of China"
            },
            {
                "Region Key": "TJ",
                "Region Name": "Tajikistan"
            },
            {
                "Region Key": "TZ",
                "Region Name": "Tanzania, United Republic of"
            },
            {
                "Region Key": "TH",
                "Region Name": "Thailand"
            },
            {
                "Region Key": "TL",
                "Region Name": "Timor-Leste"
            },
            {
                "Region Key": "TG",
                "Region Name": "Togo"
            },
            {
                "Region Key": "TK",
                "Region Name": "Tokelau"
            },
            {
                "Region Key": "TO",
                "Region Name": "Tonga"
            },
            {
                "Region Key": "TT",
                "Region Name": "Trinidad and Tobago"
            },
            {
                "Region Key": "TN",
                "Region Name": "Tunisia"
            },
            {
                "Region Key": "TR",
                "Region Name": "T\u00fcrkiye"
            },
            {
                "Region Key": "TM",
                "Region Name": "Turkmenistan"
            },
            {
                "Region Key": "TC",
                "Region Name": "Turks and Caicos Islands"
            },
            {
                "Region Key": "TV",
                "Region Name": "Tuvalu"
            },
            {
                "Region Key": "UG",
                "Region Name": "Uganda"
            },
            {
                "Region Key": "UA",
                "Region Name": "Ukraine"
            },
            {
                "Region Key": "AE",
                "Region Name": "United Arab Emirates"
            },
            {
                "Region Key": "GB",
                "Region Name": "United Kingdom"
            },
            {
                "Region Key": "US",
                "Region Name": "United States"
            },
            {
                "Region Key": "UY",
                "Region Name": "Uruguay"
            },
            {
                "Region Key": "VI",
                "Region Name": "Virgin Islands, U.S."
            },
            {
                "Region Key": "UZ",
                "Region Name": "Uzbekistan"
            },
            {
                "Region Key": "VU",
                "Region Name": "Vanuatu"
            },
            {
                "Region Key": "VA",
                "Region Name": "Holy See (Vatican City State)"
            },
            {
                "Region Key": "VE",
                "Region Name": "Venezuela, Bolivarian Republic"
            },
            {
                "Region Key": "VN",
                "Region Name": "Viet Nam"
            },
            {
                "Region Key": "VG",
                "Region Name": "Virgin Islands, British"
            },
            {
                "Region Key": "PS",
                "Region Name": "Palestine, State of"
            },
            {
                "Region Key": "EH",
                "Region Name": "Western Sahara"
            },
            {
                "Region Key": "YE",
                "Region Name": "Yemen"
            },
            {
                "Region Key": "ZM",
                "Region Name": "Zambia"
            },
            {
                "Region Key": "ZW",
                "Region Name": "Zimbabwe"
            },
            {
                "Region Key": "Countries_Reported",
                "Region Name": "Countries_Reported"
            },
            {
                "Region Key": "U2",
                "Region Name": "Euro Area (Member States and Institutions of the Euro Area) changing composition"
            },
            {
                "Region Key": "All Countries",
                "Region Name": "All Countries"
            },
            {
                "Region Key": "All Reporting Countries",
                "Region Name": "All Reporting Countries"
            }
        ],
        "Indicators": {
            "Consumer Price Index": {
                "All items": {
                    "Indicator Key": "PCPIHA_PC_CP_A_PT",
                    "Indicator Name": "Consumer Price Index, All items, Harmonized, Percentage change, Previous year",
                    "Indicator Database": "CPI",
                    "Example Frequency": "A",
                    "Example Region": "France",
                    "Example Region Code": "FR",
                    "Example URL (Period Specified)": "http://dataservices.imf.org/REST/SDMX_JSON.svc/CompactData/CPI/A.FR.PCPIHA_PC_CP_A_PT?startPeriod=2021-01-01&endPeriod=2023-01-01",
                    "Example URL (Complete Period)": "http://dataservices.imf.org/REST/SDMX_JSON.svc/CompactData/CPI/A.FR.PCPIHA_PC_CP_A_PT",
                    "Example URL Description": "Returns the Consumer Price Index, All items, Harmonized, Percentage change, Previous year indicator for France at A frequency."
                }
            },
            "Food and non-alcoholic beverages": {
                "General": {
                    "Indicator Key": "PCPIF_IX",
                    "Indicator Name": "Food and non-alcoholic beverages",
                    "Indicator Database": "CPI",
                    "Example Frequency": "A",
                    "Example Region": "France",
                    "Example Region Code": "FR",
                    "Example URL (Period Specified)": "http://dataservices.imf.org/REST/SDMX_JSON.svc/CompactData/CPI/A.FR.PCPIF_IX?startPeriod=2021-01-01&endPeriod=2023-01-01",
                    "Example URL (Complete Period)": "http://dataservices.imf.org/REST/SDMX_JSON.svc/CompactData/CPI/A.FR.PCPIF_IX",
                    "Example URL Description": "Returns the Food and non-alcoholic beverages indicator for France at A frequency."
                },
                "Overlap": {
                    "Indicator Key": "PCPIF_OLP_IX",
                    "Indicator Name": "Food and non-alcoholic beverages, Overlap",
                    "Indicator Database": "CPI",
                    "Example Frequency": "A",
                    "Example Region": "France",
                    "Example Region Code": "FR",
                    "Example URL (Period Specified)": "http://dataservices.imf.org/REST/SDMX_JSON.svc/CompactData/CPI/A.FR.PCPIF_OLP_IX?startPeriod=2021-01-01&endPeriod=2023-01-01",
                    "Example URL (Complete Period)": "http://dataservices.imf.org/REST/SDMX_JSON.svc/CompactData/CPI/A.FR.PCPIF_OLP_IX",
                    "Example URL Description": "Returns the Food and non-alcoholic beverages, Overlap indicator for France at A frequency."
                },
                "Weight": {
                    "Indicator Key": "PCPIF_WT_PT",
                    "Indicator Name": "Food and non-alcoholic beverages, Weight, Percent",
                    "Indicator Database": "CPI",
                    "Example Frequency": "A",
                    "Example Region": "France",
                    "Example Region Code": "FR",
                    "Example URL (Period Specified)": "http://dataservices.imf.org/REST/SDMX_JSON.svc/CompactData/CPI/A.FR.PCPIF_WT_PT?startPeriod=2021-01-01&endPeriod=2023-01-01",
                    "Example URL (Complete Period)": "http://dataservices.imf.org/REST/SDMX_JSON.svc/CompactData/CPI/A.FR.PCPIF_WT_PT",
                    "Example URL Description": "Returns the Food and non-alcoholic beverages, Weight, Percent indicator for France at A frequency."
                },
                "Harmonized": {
                    "Indicator Key": "PCPIHAF_WT_PT",
                    "Indicator Name": "Food and non-alcoholic beverages, Harmonized, Weight, Percent",
                    "Indicator Database": "CPI",
                    "Example Frequency": "A",
                    "Example Region": "France",
                    "Example Region Code": "FR",
                    "Example URL (Period Specified)": "http://dataservices.imf.org/REST/SDMX_JSON.svc/CompactData/CPI/A.FR.PCPIHAF_WT_PT?startPeriod=2021-01-01&endPeriod=2023-01-01",
                    "Example URL (Complete Period)": "http://dataservices.imf.org/REST/SDMX_JSON.svc/CompactData/CPI/A.FR.PCPIHAF_WT_PT",
                    "Example URL Description": "Returns the Food and non-alcoholic beverages, Harmonized, Weight, Percent indicator for France at A frequency."
                },
                "Standard Reference Period": {
                    "Indicator Key": "PCPIF_SRP_IX",
                    "Indicator Name": "Food and non-alcoholic beverages, Standard Reference Period",
                    "Indicator Database": "CPI",
                    "Example Frequency": "A",
                    "Example Region": "France",
                    "Example Region Code": "FR",
                    "Example URL (Period Specified)": "http://dataservices.imf.org/REST/SDMX_JSON.svc/CompactData/CPI/A.FR.PCPIF_SRP_IX?startPeriod=2021-01-01&endPeriod=2023-01-01",
                    "Example URL (Complete Period)": "http://dataservices.imf.org/REST/SDMX_JSON.svc/CompactData/CPI/A.FR.PCPIF_SRP_IX",
                    "Example URL Description": "Returns the Food and non-alcoholic beverages, Standard Reference Period indicator for France at A frequency."
                },
                "Percentage change": {
                    "Indicator Key": "PCPIF_PC_CP_A_PT",
                    "Indicator Name": "Food and non-alcoholic beverages, Percentage change, Previous year",
                    "Indicator Database": "CPI",
                    "Example Frequency": "A",
                    "Example Region": "France",
                    "Example Region Code": "FR",
                    "Example URL (Period Specified)": "http://dataservices.imf.org/REST/SDMX_JSON.svc/CompactData/CPI/A.FR.PCPIF_PC_CP_A_PT?startPeriod=2021-01-01&endPeriod=2023-01-01",
                    "Example URL (Complete Period)": "http://dataservices.imf.org/REST/SDMX_JSON.svc/CompactData/CPI/A.FR.PCPIF_PC_CP_A_PT",
                    "Example URL Description": "Returns the Food and non-alcoholic beverages, Percentage change, Previous year indicator for France at A frequency."
                }
            },
            "Alcoholic Beverages": {
                "Tobacco": {
                    "Indicator Key": "PCPIHABT_WT_PT",
                    "Indicator Name": "Alcoholic Beverages, Tobacco, and Narcotics, Harmonized, Weight, Percent",
                    "Indicator Database": "CPI",
                    "Example Frequency": "A",
                    "Example Region": "France",
                    "Example Region Code": "FR",
                    "Example URL (Period Specified)": "http://dataservices.imf.org/REST/SDMX_JSON.svc/CompactData/CPI/A.FR.PCPIHABT_WT_PT?startPeriod=2021-01-01&endPeriod=2023-01-01",
                    "Example URL (Complete Period)": "http://dataservices.imf.org/REST/SDMX_JSON.svc/CompactData/CPI/A.FR.PCPIHABT_WT_PT",
                    "Example URL Description": "Returns the Alcoholic Beverages, Tobacco, and Narcotics, Harmonized, Weight, Percent indicator for France at A frequency."
                }
            },
            "Clothing and footwear": {
                "General": {
                    "Indicator Key": "PCPIA_IX",
                    "Indicator Name": "Clothing and footwear",
                    "Indicator Database": "CPI",
                    "Example Frequency": "A",
                    "Example Region": "France",
                    "Example Region Code": "FR",
                    "Example URL (Period Specified)": "http://dataservices.imf.org/REST/SDMX_JSON.svc/CompactData/CPI/A.FR.PCPIA_IX?startPeriod=2021-01-01&endPeriod=2023-01-01",
                    "Example URL (Complete Period)": "http://dataservices.imf.org/REST/SDMX_JSON.svc/CompactData/CPI/A.FR.PCPIA_IX",
                    "Example URL Description": "Returns the Clothing and footwear indicator for France at A frequency."
                },
                "Overlap": {
                    "Indicator Key": "PCPIA_OLP_IX",
                    "Indicator Name": "Clothing and footwear, Overlap",
                    "Indicator Database": "CPI",
                    "Example Frequency": "A",
                    "Example Region": "France",
                    "Example Region Code": "FR",
                    "Example URL (Period Specified)": "http://dataservices.imf.org/REST/SDMX_JSON.svc/CompactData/CPI/A.FR.PCPIA_OLP_IX?startPeriod=2021-01-01&endPeriod=2023-01-01",
                    "Example URL (Complete Period)": "http://dataservices.imf.org/REST/SDMX_JSON.svc/CompactData/CPI/A.FR.PCPIA_OLP_IX",
                    "Example URL Description": "Returns the Clothing and footwear, Overlap indicator for France at A frequency."
                },
                "Weight": {
                    "Indicator Key": "PCPIA_WT_PT",
                    "Indicator Name": "Clothing and footwear, Weight, Percent",
                    "Indicator Database": "CPI",
                    "Example Frequency": "A",
                    "Example Region": "France",
                    "Example Region Code": "FR",
                    "Example URL (Period Specified)": "http://dataservices.imf.org/REST/SDMX_JSON.svc/CompactData/CPI/A.FR.PCPIA_WT_PT?startPeriod=2021-01-01&endPeriod=2023-01-01",
                    "Example URL (Complete Period)": "http://dataservices.imf.org/REST/SDMX_JSON.svc/CompactData/CPI/A.FR.PCPIA_WT_PT",
                    "Example URL Description": "Returns the Clothing and footwear, Weight, Percent indicator for France at A frequency."
                },
                "Harmonized": {
                    "Indicator Key": "PCPIHAA_WT_PT",
                    "Indicator Name": "Clothing and footwear, Harmonized, Weight, Percent",
                    "Indicator Database": "CPI",
                    "Example Frequency": "A",
                    "Example Region": "France",
                    "Example Region Code": "FR",
                    "Example URL (Period Specified)": "http://dataservices.imf.org/REST/SDMX_JSON.svc/CompactData/CPI/A.FR.PCPIHAA_WT_PT?startPeriod=2021-01-01&endPeriod=2023-01-01",
                    "Example URL (Complete Period)": "http://dataservices.imf.org/REST/SDMX_JSON.svc/CompactData/CPI/A.FR.PCPIHAA_WT_PT",
                    "Example URL Description": "Returns the Clothing and footwear, Harmonized, Weight, Percent indicator for France at A frequency."
                },
                "Standard Reference Period": {
                    "Indicator Key": "PCPIA_SRP_IX",
                    "Indicator Name": "Clothing and footwear, Standard Reference Period",
                    "Indicator Database": "CPI",
                    "Example Frequency": "A",
                    "Example Region": "France",
                    "Example Region Code": "FR",
                    "Example URL (Period Specified)": "http://dataservices.imf.org/REST/SDMX_JSON.svc/CompactData/CPI/A.FR.PCPIA_SRP_IX?startPeriod=2021-01-01&endPeriod=2023-01-01",
                    "Example URL (Complete Period)": "http://dataservices.imf.org/REST/SDMX_JSON.svc/CompactData/CPI/A.FR.PCPIA_SRP_IX",
                    "Example URL Description": "Returns the Clothing and footwear, Standard Reference Period indicator for France at A frequency."
                },
                "Percentage change": {
                    "Indicator Key": "PCPIA_PC_CP_A_PT",
                    "Indicator Name": "Clothing and footwear, Percentage change, Previous year",
                    "Indicator Database": "CPI",
                    "Example Frequency": "A",
                    "Example Region": "France",
                    "Example Region Code": "FR",
                    "Example URL (Period Specified)": "http://dataservices.imf.org/REST/SDMX_JSON.svc/CompactData/CPI/A.FR.PCPIA_PC_CP_A_PT?startPeriod=2021-01-01&endPeriod=2023-01-01",
                    "Example URL (Complete Period)": "http://dataservices.imf.org/REST/SDMX_JSON.svc/CompactData/CPI/A.FR.PCPIA_PC_CP_A_PT",
                    "Example URL Description": "Returns the Clothing and footwear, Percentage change, Previous year indicator for France at A frequency."
                }
            },
            "Housing": {
                "Water": {
                    "Indicator Key": "PCPIHAH_WT_PT",
                    "Indicator Name": "Housing, Water, Electricity, Gas and Other Fuels, Harmonized, Weight, Percent",
                    "Indicator Database": "CPI",
                    "Example Frequency": "A",
                    "Example Region": "France",
                    "Example Region Code": "FR",
                    "Example URL (Period Specified)": "http://dataservices.imf.org/REST/SDMX_JSON.svc/CompactData/CPI/A.FR.PCPIHAH_WT_PT?startPeriod=2021-01-01&endPeriod=2023-01-01",
                    "Example URL (Complete Period)": "http://dataservices.imf.org/REST/SDMX_JSON.svc/CompactData/CPI/A.FR.PCPIHAH_WT_PT",
                    "Example URL Description": "Returns the Housing, Water, Electricity, Gas and Other Fuels, Harmonized, Weight, Percent indicator for France at A frequency."
                }
            },
            "Furnishings": {
                "household equipment and routine household maintenance": {
                    "Indicator Key": "PCPIHAHO_WT_PT",
                    "Indicator Name": "Furnishings, household equipment and routine household maintenance, Harmonized, Weight, Percent",
                    "Indicator Database": "CPI",
                    "Example Frequency": "A",
                    "Example Region": "France",
                    "Example Region Code": "FR",
                    "Example URL (Period Specified)": "http://dataservices.imf.org/REST/SDMX_JSON.svc/CompactData/CPI/A.FR.PCPIHAHO_WT_PT?startPeriod=2021-01-01&endPeriod=2023-01-01",
                    "Example URL (Complete Period)": "http://dataservices.imf.org/REST/SDMX_JSON.svc/CompactData/CPI/A.FR.PCPIHAHO_WT_PT",
                    "Example URL Description": "Returns the Furnishings, household equipment and routine household maintenance, Harmonized, Weight, Percent indicator for France at A frequency."
                }
            },
            "Health": {
                "General": {
                    "Indicator Key": "PCPIM_IX",
                    "Indicator Name": "Health",
                    "Indicator Database": "CPI",
                    "Example Frequency": "A",
                    "Example Region": "France",
                    "Example Region Code": "FR",
                    "Example URL (Period Specified)": "http://dataservices.imf.org/REST/SDMX_JSON.svc/CompactData/CPI/A.FR.PCPIM_IX?startPeriod=2021-01-01&endPeriod=2023-01-01",
                    "Example URL (Complete Period)": "http://dataservices.imf.org/REST/SDMX_JSON.svc/CompactData/CPI/A.FR.PCPIM_IX",
                    "Example URL Description": "Returns the Health indicator for France at A frequency."
                },
                "Overlap": {
                    "Indicator Key": "PCPIM_OLP_IX",
                    "Indicator Name": "Health, Overlap",
                    "Indicator Database": "CPI",
                    "Example Frequency": "A",
                    "Example Region": "France",
                    "Example Region Code": "FR",
                    "Example URL (Period Specified)": "http://dataservices.imf.org/REST/SDMX_JSON.svc/CompactData/CPI/A.FR.PCPIM_OLP_IX?startPeriod=2021-01-01&endPeriod=2023-01-01",
                    "Example URL (Complete Period)": "http://dataservices.imf.org/REST/SDMX_JSON.svc/CompactData/CPI/A.FR.PCPIM_OLP_IX",
                    "Example URL Description": "Returns the Health, Overlap indicator for France at A frequency."
                },
                "Weight": {
                    "Indicator Key": "PCPIM_WT_PT",
                    "Indicator Name": "Health, Weight, Percent",
                    "Indicator Database": "CPI",
                    "Example Frequency": "A",
                    "Example Region": "France",
                    "Example Region Code": "FR",
                    "Example URL (Period Specified)": "http://dataservices.imf.org/REST/SDMX_JSON.svc/CompactData/CPI/A.FR.PCPIM_WT_PT?startPeriod=2021-01-01&endPeriod=2023-01-01",
                    "Example URL (Complete Period)": "http://dataservices.imf.org/REST/SDMX_JSON.svc/CompactData/CPI/A.FR.PCPIM_WT_PT",
                    "Example URL Description": "Returns the Health, Weight, Percent indicator for France at A frequency."
                },
                "Harmonized": {
                    "Indicator Key": "PCPIHAM_WT_PT",
                    "Indicator Name": "Health, Harmonized, Weight, Percent",
                    "Indicator Database": "CPI",
                    "Example Frequency": "A",
                    "Example Region": "France",
                    "Example Region Code": "FR",
                    "Example URL (Period Specified)": "http://dataservices.imf.org/REST/SDMX_JSON.svc/CompactData/CPI/A.FR.PCPIHAM_WT_PT?startPeriod=2021-01-01&endPeriod=2023-01-01",
                    "Example URL (Complete Period)": "http://dataservices.imf.org/REST/SDMX_JSON.svc/CompactData/CPI/A.FR.PCPIHAM_WT_PT",
                    "Example URL Description": "Returns the Health, Harmonized, Weight, Percent indicator for France at A frequency."
                },
                "Standard Reference Period": {
                    "Indicator Key": "PCPIM_SRP_IX",
                    "Indicator Name": "Health, Standard Reference Period",
                    "Indicator Database": "CPI",
                    "Example Frequency": "A",
                    "Example Region": "France",
                    "Example Region Code": "FR",
                    "Example URL (Period Specified)": "http://dataservices.imf.org/REST/SDMX_JSON.svc/CompactData/CPI/A.FR.PCPIM_SRP_IX?startPeriod=2021-01-01&endPeriod=2023-01-01",
                    "Example URL (Complete Period)": "http://dataservices.imf.org/REST/SDMX_JSON.svc/CompactData/CPI/A.FR.PCPIM_SRP_IX",
                    "Example URL Description": "Returns the Health, Standard Reference Period indicator for France at A frequency."
                },
                "Percentage change": {
                    "Indicator Key": "PCPIM_PC_CP_A_PT",
                    "Indicator Name": "Health, Percentage change, Previous year",
                    "Indicator Database": "CPI",
                    "Example Frequency": "A",
                    "Example Region": "France",
                    "Example Region Code": "FR",
                    "Example URL (Period Specified)": "http://dataservices.imf.org/REST/SDMX_JSON.svc/CompactData/CPI/A.FR.PCPIM_PC_CP_A_PT?startPeriod=2021-01-01&endPeriod=2023-01-01",
                    "Example URL (Complete Period)": "http://dataservices.imf.org/REST/SDMX_JSON.svc/CompactData/CPI/A.FR.PCPIM_PC_CP_A_PT",
                    "Example URL Description": "Returns the Health, Percentage change, Previous year indicator for France at A frequency."
                }
            },
            "Transport": {
                "General": {
                    "Indicator Key": "PCPIT_IX",
                    "Indicator Name": "Transport",
                    "Indicator Database": "CPI",
                    "Example Frequency": "A",
                    "Example Region": "France",
                    "Example Region Code": "FR",
                    "Example URL (Period Specified)": "http://dataservices.imf.org/REST/SDMX_JSON.svc/CompactData/CPI/A.FR.PCPIT_IX?startPeriod=2021-01-01&endPeriod=2023-01-01",
                    "Example URL (Complete Period)": "http://dataservices.imf.org/REST/SDMX_JSON.svc/CompactData/CPI/A.FR.PCPIT_IX",
                    "Example URL Description": "Returns the Transport indicator for France at A frequency."
                },
                "Overlap": {
                    "Indicator Key": "PCPIT_OLP_IX",
                    "Indicator Name": "Transport, Overlap",
                    "Indicator Database": "CPI",
                    "Example Frequency": "A",
                    "Example Region": "France",
                    "Example Region Code": "FR",
                    "Example URL (Period Specified)": "http://dataservices.imf.org/REST/SDMX_JSON.svc/CompactData/CPI/A.FR.PCPIT_OLP_IX?startPeriod=2021-01-01&endPeriod=2023-01-01",
                    "Example URL (Complete Period)": "http://dataservices.imf.org/REST/SDMX_JSON.svc/CompactData/CPI/A.FR.PCPIT_OLP_IX",
                    "Example URL Description": "Returns the Transport, Overlap indicator for France at A frequency."
                },
                "Weight": {
                    "Indicator Key": "PCPIT_WT_PT",
                    "Indicator Name": "Transport, Weight, Percent",
                    "Indicator Database": "CPI",
                    "Example Frequency": "A",
                    "Example Region": "France",
                    "Example Region Code": "FR",
                    "Example URL (Period Specified)": "http://dataservices.imf.org/REST/SDMX_JSON.svc/CompactData/CPI/A.FR.PCPIT_WT_PT?startPeriod=2021-01-01&endPeriod=2023-01-01",
                    "Example URL (Complete Period)": "http://dataservices.imf.org/REST/SDMX_JSON.svc/CompactData/CPI/A.FR.PCPIT_WT_PT",
                    "Example URL Description": "Returns the Transport, Weight, Percent indicator for France at A frequency."
                },
                "Harmonized": {
                    "Indicator Key": "PCPIHAT_WT_PT",
                    "Indicator Name": "Transport, Harmonized, Weight, Percent",
                    "Indicator Database": "CPI",
                    "Example Frequency": "A",
                    "Example Region": "France",
                    "Example Region Code": "FR",
                    "Example URL (Period Specified)": "http://dataservices.imf.org/REST/SDMX_JSON.svc/CompactData/CPI/A.FR.PCPIHAT_WT_PT?startPeriod=2021-01-01&endPeriod=2023-01-01",
                    "Example URL (Complete Period)": "http://dataservices.imf.org/REST/SDMX_JSON.svc/CompactData/CPI/A.FR.PCPIHAT_WT_PT",
                    "Example URL Description": "Returns the Transport, Harmonized, Weight, Percent indicator for France at A frequency."
                },
                "Standard Reference Period": {
                    "Indicator Key": "PCPIT_SRP_IX",
                    "Indicator Name": "Transport, Standard Reference Period",
                    "Indicator Database": "CPI",
                    "Example Frequency": "A",
                    "Example Region": "France",
                    "Example Region Code": "FR",
                    "Example URL (Period Specified)": "http://dataservices.imf.org/REST/SDMX_JSON.svc/CompactData/CPI/A.FR.PCPIT_SRP_IX?startPeriod=2021-01-01&endPeriod=2023-01-01",
                    "Example URL (Complete Period)": "http://dataservices.imf.org/REST/SDMX_JSON.svc/CompactData/CPI/A.FR.PCPIT_SRP_IX",
                    "Example URL Description": "Returns the Transport, Standard Reference Period indicator for France at A frequency."
                },
                "Percentage change": {
                    "Indicator Key": "PCPIT_PC_CP_A_PT",
                    "Indicator Name": "Transport, Percentage change, Previous year",
                    "Indicator Database": "CPI",
                    "Example Frequency": "A",
                    "Example Region": "France",
                    "Example Region Code": "FR",
                    "Example URL (Period Specified)": "http://dataservices.imf.org/REST/SDMX_JSON.svc/CompactData/CPI/A.FR.PCPIT_PC_CP_A_PT?startPeriod=2021-01-01&endPeriod=2023-01-01",
                    "Example URL (Complete Period)": "http://dataservices.imf.org/REST/SDMX_JSON.svc/CompactData/CPI/A.FR.PCPIT_PC_CP_A_PT",
                    "Example URL Description": "Returns the Transport, Percentage change, Previous year indicator for France at A frequency."
                }
            },
            "Communication": {
                "General": {
                    "Indicator Key": "PCPIEC_IX",
                    "Indicator Name": "Communication",
                    "Indicator Database": "CPI",
                    "Example Frequency": "A",
                    "Example Region": "France",
                    "Example Region Code": "FR",
                    "Example URL (Period Specified)": "http://dataservices.imf.org/REST/SDMX_JSON.svc/CompactData/CPI/A.FR.PCPIEC_IX?startPeriod=2021-01-01&endPeriod=2023-01-01",
                    "Example URL (Complete Period)": "http://dataservices.imf.org/REST/SDMX_JSON.svc/CompactData/CPI/A.FR.PCPIEC_IX",
                    "Example URL Description": "Returns the Communication indicator for France at A frequency."
                },
                "Overlap": {
                    "Indicator Key": "PCPIEC_OLP_IX",
                    "Indicator Name": "Communication, Overlap",
                    "Indicator Database": "CPI",
                    "Example Frequency": "A",
                    "Example Region": "France",
                    "Example Region Code": "FR",
                    "Example URL (Period Specified)": "http://dataservices.imf.org/REST/SDMX_JSON.svc/CompactData/CPI/A.FR.PCPIEC_OLP_IX?startPeriod=2021-01-01&endPeriod=2023-01-01",
                    "Example URL (Complete Period)": "http://dataservices.imf.org/REST/SDMX_JSON.svc/CompactData/CPI/A.FR.PCPIEC_OLP_IX",
                    "Example URL Description": "Returns the Communication, Overlap indicator for France at A frequency."
                },
                "Weight": {
                    "Indicator Key": "PCPIEC_WT_PT",
                    "Indicator Name": "Communication, Weight, Percent",
                    "Indicator Database": "CPI",
                    "Example Frequency": "A",
                    "Example Region": "France",
                    "Example Region Code": "FR",
                    "Example URL (Period Specified)": "http://dataservices.imf.org/REST/SDMX_JSON.svc/CompactData/CPI/A.FR.PCPIEC_WT_PT?startPeriod=2021-01-01&endPeriod=2023-01-01",
                    "Example URL (Complete Period)": "http://dataservices.imf.org/REST/SDMX_JSON.svc/CompactData/CPI/A.FR.PCPIEC_WT_PT",
                    "Example URL Description": "Returns the Communication, Weight, Percent indicator for France at A frequency."
                },
                "Harmonized": {
                    "Indicator Key": "PCPIHAC_WT_PT",
                    "Indicator Name": "Communication, Harmonized, Weight, Percent",
                    "Indicator Database": "CPI",
                    "Example Frequency": "A",
                    "Example Region": "France",
                    "Example Region Code": "FR",
                    "Example URL (Period Specified)": "http://dataservices.imf.org/REST/SDMX_JSON.svc/CompactData/CPI/A.FR.PCPIHAC_WT_PT?startPeriod=2021-01-01&endPeriod=2023-01-01",
                    "Example URL (Complete Period)": "http://dataservices.imf.org/REST/SDMX_JSON.svc/CompactData/CPI/A.FR.PCPIHAC_WT_PT",
                    "Example URL Description": "Returns the Communication, Harmonized, Weight, Percent indicator for France at A frequency."
                },
                "Standard Reference Period": {
                    "Indicator Key": "PCPIEC_SRP_IX",
                    "Indicator Name": "Communication, Standard Reference Period",
                    "Indicator Database": "CPI",
                    "Example Frequency": "A",
                    "Example Region": "France",
                    "Example Region Code": "FR",
                    "Example URL (Period Specified)": "http://dataservices.imf.org/REST/SDMX_JSON.svc/CompactData/CPI/A.FR.PCPIEC_SRP_IX?startPeriod=2021-01-01&endPeriod=2023-01-01",
                    "Example URL (Complete Period)": "http://dataservices.imf.org/REST/SDMX_JSON.svc/CompactData/CPI/A.FR.PCPIEC_SRP_IX",
                    "Example URL Description": "Returns the Communication, Standard Reference Period indicator for France at A frequency."
                },
                "Percentage change": {
                    "Indicator Key": "PCPIEC_PC_CP_A_PT",
                    "Indicator Name": "Communication, Percentage change, Previous year",
                    "Indicator Database": "CPI",
                    "Example Frequency": "A",
                    "Example Region": "France",
                    "Example Region Code": "FR",
                    "Example URL (Period Specified)": "http://dataservices.imf.org/REST/SDMX_JSON.svc/CompactData/CPI/A.FR.PCPIEC_PC_CP_A_PT?startPeriod=2021-01-01&endPeriod=2023-01-01",
                    "Example URL (Complete Period)": "http://dataservices.imf.org/REST/SDMX_JSON.svc/CompactData/CPI/A.FR.PCPIEC_PC_CP_A_PT",
                    "Example URL Description": "Returns the Communication, Percentage change, Previous year indicator for France at A frequency."
                }
            },
            "Recreation and culture": {
                "General": {
                    "Indicator Key": "PCPIR_IX",
                    "Indicator Name": "Recreation and culture",
                    "Indicator Database": "CPI",
                    "Example Frequency": "A",
                    "Example Region": "France",
                    "Example Region Code": "FR",
                    "Example URL (Period Specified)": "http://dataservices.imf.org/REST/SDMX_JSON.svc/CompactData/CPI/A.FR.PCPIR_IX?startPeriod=2021-01-01&endPeriod=2023-01-01",
                    "Example URL (Complete Period)": "http://dataservices.imf.org/REST/SDMX_JSON.svc/CompactData/CPI/A.FR.PCPIR_IX",
                    "Example URL Description": "Returns the Recreation and culture indicator for France at A frequency."
                },
                "Overlap": {
                    "Indicator Key": "PCPIR_OLP_IX",
                    "Indicator Name": "Recreation and culture, Overlap",
                    "Indicator Database": "CPI",
                    "Example Frequency": "A",
                    "Example Region": "France",
                    "Example Region Code": "FR",
                    "Example URL (Period Specified)": "http://dataservices.imf.org/REST/SDMX_JSON.svc/CompactData/CPI/A.FR.PCPIR_OLP_IX?startPeriod=2021-01-01&endPeriod=2023-01-01",
                    "Example URL (Complete Period)": "http://dataservices.imf.org/REST/SDMX_JSON.svc/CompactData/CPI/A.FR.PCPIR_OLP_IX",
                    "Example URL Description": "Returns the Recreation and culture, Overlap indicator for France at A frequency."
                },
                "Weight": {
                    "Indicator Key": "PCPIR_WT_PT",
                    "Indicator Name": "Recreation and culture, Weight, Percent",
                    "Indicator Database": "CPI",
                    "Example Frequency": "A",
                    "Example Region": "France",
                    "Example Region Code": "FR",
                    "Example URL (Period Specified)": "http://dataservices.imf.org/REST/SDMX_JSON.svc/CompactData/CPI/A.FR.PCPIR_WT_PT?startPeriod=2021-01-01&endPeriod=2023-01-01",
                    "Example URL (Complete Period)": "http://dataservices.imf.org/REST/SDMX_JSON.svc/CompactData/CPI/A.FR.PCPIR_WT_PT",
                    "Example URL Description": "Returns the Recreation and culture, Weight, Percent indicator for France at A frequency."
                },
                "Harmonized": {
                    "Indicator Key": "PCPIHARC_WT_PT",
                    "Indicator Name": "Recreation and culture, Harmonized, Weight, Percent",
                    "Indicator Database": "CPI",
                    "Example Frequency": "A",
                    "Example Region": "France",
                    "Example Region Code": "FR",
                    "Example URL (Period Specified)": "http://dataservices.imf.org/REST/SDMX_JSON.svc/CompactData/CPI/A.FR.PCPIHARC_WT_PT?startPeriod=2021-01-01&endPeriod=2023-01-01",
                    "Example URL (Complete Period)": "http://dataservices.imf.org/REST/SDMX_JSON.svc/CompactData/CPI/A.FR.PCPIHARC_WT_PT",
                    "Example URL Description": "Returns the Recreation and culture, Harmonized, Weight, Percent indicator for France at A frequency."
                },
                "Standard Reference Period": {
                    "Indicator Key": "PCPIR_SRP_IX",
                    "Indicator Name": "Recreation and culture, Standard Reference Period",
                    "Indicator Database": "CPI",
                    "Example Frequency": "A",
                    "Example Region": "France",
                    "Example Region Code": "FR",
                    "Example URL (Period Specified)": "http://dataservices.imf.org/REST/SDMX_JSON.svc/CompactData/CPI/A.FR.PCPIR_SRP_IX?startPeriod=2021-01-01&endPeriod=2023-01-01",
                    "Example URL (Complete Period)": "http://dataservices.imf.org/REST/SDMX_JSON.svc/CompactData/CPI/A.FR.PCPIR_SRP_IX",
                    "Example URL Description": "Returns the Recreation and culture, Standard Reference Period indicator for France at A frequency."
                },
                "Percentage change": {
                    "Indicator Key": "PCPIR_PC_CP_A_PT",
                    "Indicator Name": "Recreation and culture, Percentage change, Previous year",
                    "Indicator Database": "CPI",
                    "Example Frequency": "A",
                    "Example Region": "France",
                    "Example Region Code": "FR",
                    "Example URL (Period Specified)": "http://dataservices.imf.org/REST/SDMX_JSON.svc/CompactData/CPI/A.FR.PCPIR_PC_CP_A_PT?startPeriod=2021-01-01&endPeriod=2023-01-01",
                    "Example URL (Complete Period)": "http://dataservices.imf.org/REST/SDMX_JSON.svc/CompactData/CPI/A.FR.PCPIR_PC_CP_A_PT",
                    "Example URL Description": "Returns the Recreation and culture, Percentage change, Previous year indicator for France at A frequency."
                }
            },
            "Education": {
                "General": {
                    "Indicator Key": "PCPIED_IX",
                    "Indicator Name": "Education",
                    "Indicator Database": "CPI",
                    "Example Frequency": "A",
                    "Example Region": "France",
                    "Example Region Code": "FR",
                    "Example URL (Period Specified)": "http://dataservices.imf.org/REST/SDMX_JSON.svc/CompactData/CPI/A.FR.PCPIED_IX?startPeriod=2021-01-01&endPeriod=2023-01-01",
                    "Example URL (Complete Period)": "http://dataservices.imf.org/REST/SDMX_JSON.svc/CompactData/CPI/A.FR.PCPIED_IX",
                    "Example URL Description": "Returns the Education indicator for France at A frequency."
                },
                "Overlap": {
                    "Indicator Key": "PCPIED_OLP_IX",
                    "Indicator Name": "Education, Overlap",
                    "Indicator Database": "CPI",
                    "Example Frequency": "A",
                    "Example Region": "France",
                    "Example Region Code": "FR",
                    "Example URL (Period Specified)": "http://dataservices.imf.org/REST/SDMX_JSON.svc/CompactData/CPI/A.FR.PCPIED_OLP_IX?startPeriod=2021-01-01&endPeriod=2023-01-01",
                    "Example URL (Complete Period)": "http://dataservices.imf.org/REST/SDMX_JSON.svc/CompactData/CPI/A.FR.PCPIED_OLP_IX",
                    "Example URL Description": "Returns the Education, Overlap indicator for France at A frequency."
                },
                "Weight": {
                    "Indicator Key": "PCPIED_WT_PT",
                    "Indicator Name": "Education, Weight, Percent",
                    "Indicator Database": "CPI",
                    "Example Frequency": "A",
                    "Example Region": "France",
                    "Example Region Code": "FR",
                    "Example URL (Period Specified)": "http://dataservices.imf.org/REST/SDMX_JSON.svc/CompactData/CPI/A.FR.PCPIED_WT_PT?startPeriod=2021-01-01&endPeriod=2023-01-01",
                    "Example URL (Complete Period)": "http://dataservices.imf.org/REST/SDMX_JSON.svc/CompactData/CPI/A.FR.PCPIED_WT_PT",
                    "Example URL Description": "Returns the Education, Weight, Percent indicator for France at A frequency."
                },
                "Harmonized": {
                    "Indicator Key": "PCPIHAED_WT_PT",
                    "Indicator Name": "Education, Harmonized, Weight, Percent",
                    "Indicator Database": "CPI",
                    "Example Frequency": "A",
                    "Example Region": "France",
                    "Example Region Code": "FR",
                    "Example URL (Period Specified)": "http://dataservices.imf.org/REST/SDMX_JSON.svc/CompactData/CPI/A.FR.PCPIHAED_WT_PT?startPeriod=2021-01-01&endPeriod=2023-01-01",
                    "Example URL (Complete Period)": "http://dataservices.imf.org/REST/SDMX_JSON.svc/CompactData/CPI/A.FR.PCPIHAED_WT_PT",
                    "Example URL Description": "Returns the Education, Harmonized, Weight, Percent indicator for France at A frequency."
                },
                "Standard Reference Period": {
                    "Indicator Key": "PCPIED_SRP_IX",
                    "Indicator Name": "Education, Standard Reference Period",
                    "Indicator Database": "CPI",
                    "Example Frequency": "A",
                    "Example Region": "France",
                    "Example Region Code": "FR",
                    "Example URL (Period Specified)": "http://dataservices.imf.org/REST/SDMX_JSON.svc/CompactData/CPI/A.FR.PCPIED_SRP_IX?startPeriod=2021-01-01&endPeriod=2023-01-01",
                    "Example URL (Complete Period)": "http://dataservices.imf.org/REST/SDMX_JSON.svc/CompactData/CPI/A.FR.PCPIED_SRP_IX",
                    "Example URL Description": "Returns the Education, Standard Reference Period indicator for France at A frequency."
                },
                "Percentage change": {
                    "Indicator Key": "PCPIED_PC_CP_A_PT",
                    "Indicator Name": "Education, Percentage change, Previous year",
                    "Indicator Database": "CPI",
                    "Example Frequency": "A",
                    "Example Region": "France",
                    "Example Region Code": "FR",
                    "Example URL (Period Specified)": "http://dataservices.imf.org/REST/SDMX_JSON.svc/CompactData/CPI/A.FR.PCPIED_PC_CP_A_PT?startPeriod=2021-01-01&endPeriod=2023-01-01",
                    "Example URL (Complete Period)": "http://dataservices.imf.org/REST/SDMX_JSON.svc/CompactData/CPI/A.FR.PCPIED_PC_CP_A_PT",
                    "Example URL Description": "Returns the Education, Percentage change, Previous year indicator for France at A frequency."
                }
            },
            "Restaurants and hotels": {
                "General": {
                    "Indicator Key": "PCPIRE_IX",
                    "Indicator Name": "Restaurants and hotels",
                    "Indicator Database": "CPI",
                    "Example Frequency": "A",
                    "Example Region": "France",
                    "Example Region Code": "FR",
                    "Example URL (Period Specified)": "http://dataservices.imf.org/REST/SDMX_JSON.svc/CompactData/CPI/A.FR.PCPIRE_IX?startPeriod=2021-01-01&endPeriod=2023-01-01",
                    "Example URL (Complete Period)": "http://dataservices.imf.org/REST/SDMX_JSON.svc/CompactData/CPI/A.FR.PCPIRE_IX",
                    "Example URL Description": "Returns the Restaurants and hotels indicator for France at A frequency."
                },
                "Overlap": {
                    "Indicator Key": "PCPIRE_OLP_IX",
                    "Indicator Name": "Restaurants and hotels, Overlap",
                    "Indicator Database": "CPI",
                    "Example Frequency": "A",
                    "Example Region": "France",
                    "Example Region Code": "FR",
                    "Example URL (Period Specified)": "http://dataservices.imf.org/REST/SDMX_JSON.svc/CompactData/CPI/A.FR.PCPIRE_OLP_IX?startPeriod=2021-01-01&endPeriod=2023-01-01",
                    "Example URL (Complete Period)": "http://dataservices.imf.org/REST/SDMX_JSON.svc/CompactData/CPI/A.FR.PCPIRE_OLP_IX",
                    "Example URL Description": "Returns the Restaurants and hotels, Overlap indicator for France at A frequency."
                },
                "Weight": {
                    "Indicator Key": "PCPIRE_WT_PT",
                    "Indicator Name": "Restaurants and hotels, Weight, Percent",
                    "Indicator Database": "CPI",
                    "Example Frequency": "A",
                    "Example Region": "France",
                    "Example Region Code": "FR",
                    "Example URL (Period Specified)": "http://dataservices.imf.org/REST/SDMX_JSON.svc/CompactData/CPI/A.FR.PCPIRE_WT_PT?startPeriod=2021-01-01&endPeriod=2023-01-01",
                    "Example URL (Complete Period)": "http://dataservices.imf.org/REST/SDMX_JSON.svc/CompactData/CPI/A.FR.PCPIRE_WT_PT",
                    "Example URL Description": "Returns the Restaurants and hotels, Weight, Percent indicator for France at A frequency."
                },
                "Harmonized": {
                    "Indicator Key": "PCPIHARE_WT_PT",
                    "Indicator Name": "Restaurants and hotels, Harmonized, Weight, Percent",
                    "Indicator Database": "CPI",
                    "Example Frequency": "A",
                    "Example Region": "France",
                    "Example Region Code": "FR",
                    "Example URL (Period Specified)": "http://dataservices.imf.org/REST/SDMX_JSON.svc/CompactData/CPI/A.FR.PCPIHARE_WT_PT?startPeriod=2021-01-01&endPeriod=2023-01-01",
                    "Example URL (Complete Period)": "http://dataservices.imf.org/REST/SDMX_JSON.svc/CompactData/CPI/A.FR.PCPIHARE_WT_PT",
                    "Example URL Description": "Returns the Restaurants and hotels, Harmonized, Weight, Percent indicator for France at A frequency."
                },
                "Standard Reference Period": {
                    "Indicator Key": "PCPIRE_SRP_IX",
                    "Indicator Name": "Restaurants and hotels, Standard Reference Period",
                    "Indicator Database": "CPI",
                    "Example Frequency": "A",
                    "Example Region": "France",
                    "Example Region Code": "FR",
                    "Example URL (Period Specified)": "http://dataservices.imf.org/REST/SDMX_JSON.svc/CompactData/CPI/A.FR.PCPIRE_SRP_IX?startPeriod=2021-01-01&endPeriod=2023-01-01",
                    "Example URL (Complete Period)": "http://dataservices.imf.org/REST/SDMX_JSON.svc/CompactData/CPI/A.FR.PCPIRE_SRP_IX",
                    "Example URL Description": "Returns the Restaurants and hotels, Standard Reference Period indicator for France at A frequency."
                },
                "Percentage change": {
                    "Indicator Key": "PCPIRE_PC_CP_A_PT",
                    "Indicator Name": "Restaurants and hotels, Percentage change, Previous year",
                    "Indicator Database": "CPI",
                    "Example Frequency": "A",
                    "Example Region": "France",
                    "Example Region Code": "FR",
                    "Example URL (Period Specified)": "http://dataservices.imf.org/REST/SDMX_JSON.svc/CompactData/CPI/A.FR.PCPIRE_PC_CP_A_PT?startPeriod=2021-01-01&endPeriod=2023-01-01",
                    "Example URL (Complete Period)": "http://dataservices.imf.org/REST/SDMX_JSON.svc/CompactData/CPI/A.FR.PCPIRE_PC_CP_A_PT",
                    "Example URL Description": "Returns the Restaurants and hotels, Percentage change, Previous year indicator for France at A frequency."
                }
            },
            "Miscellaneous goods and services": {
                "General": {
                    "Indicator Key": "PCPIO_IX",
                    "Indicator Name": "Miscellaneous goods and services",
                    "Indicator Database": "CPI",
                    "Example Frequency": "A",
                    "Example Region": "France",
                    "Example Region Code": "FR",
                    "Example URL (Period Specified)": "http://dataservices.imf.org/REST/SDMX_JSON.svc/CompactData/CPI/A.FR.PCPIO_IX?startPeriod=2021-01-01&endPeriod=2023-01-01",
                    "Example URL (Complete Period)": "http://dataservices.imf.org/REST/SDMX_JSON.svc/CompactData/CPI/A.FR.PCPIO_IX",
                    "Example URL Description": "Returns the Miscellaneous goods and services indicator for France at A frequency."
                },
                "Overlap": {
                    "Indicator Key": "PCPIO_OLP_IX",
                    "Indicator Name": "Miscellaneous goods and services, Overlap",
                    "Indicator Database": "CPI",
                    "Example Frequency": "A",
                    "Example Region": "France",
                    "Example Region Code": "FR",
                    "Example URL (Period Specified)": "http://dataservices.imf.org/REST/SDMX_JSON.svc/CompactData/CPI/A.FR.PCPIO_OLP_IX?startPeriod=2021-01-01&endPeriod=2023-01-01",
                    "Example URL (Complete Period)": "http://dataservices.imf.org/REST/SDMX_JSON.svc/CompactData/CPI/A.FR.PCPIO_OLP_IX",
                    "Example URL Description": "Returns the Miscellaneous goods and services, Overlap indicator for France at A frequency."
                },
                "Weight": {
                    "Indicator Key": "PCPIO_WT_PT",
                    "Indicator Name": "Miscellaneous goods and services, Weight, Percent",
                    "Indicator Database": "CPI",
                    "Example Frequency": "A",
                    "Example Region": "France",
                    "Example Region Code": "FR",
                    "Example URL (Period Specified)": "http://dataservices.imf.org/REST/SDMX_JSON.svc/CompactData/CPI/A.FR.PCPIO_WT_PT?startPeriod=2021-01-01&endPeriod=2023-01-01",
                    "Example URL (Complete Period)": "http://dataservices.imf.org/REST/SDMX_JSON.svc/CompactData/CPI/A.FR.PCPIO_WT_PT",
                    "Example URL Description": "Returns the Miscellaneous goods and services, Weight, Percent indicator for France at A frequency."
                },
                "Harmonized": {
                    "Indicator Key": "PCPIHAO_WT_PT",
                    "Indicator Name": "Miscellaneous goods and services, Harmonized, Weight, Percent",
                    "Indicator Database": "CPI",
                    "Example Frequency": "A",
                    "Example Region": "France",
                    "Example Region Code": "FR",
                    "Example URL (Period Specified)": "http://dataservices.imf.org/REST/SDMX_JSON.svc/CompactData/CPI/A.FR.PCPIHAO_WT_PT?startPeriod=2021-01-01&endPeriod=2023-01-01",
                    "Example URL (Complete Period)": "http://dataservices.imf.org/REST/SDMX_JSON.svc/CompactData/CPI/A.FR.PCPIHAO_WT_PT",
                    "Example URL Description": "Returns the Miscellaneous goods and services, Harmonized, Weight, Percent indicator for France at A frequency."
                },
                "Standard Reference Period": {
                    "Indicator Key": "PCPIO_SRP_IX",
                    "Indicator Name": "Miscellaneous goods and services, Standard Reference Period",
                    "Indicator Database": "CPI",
                    "Example Frequency": "A",
                    "Example Region": "France",
                    "Example Region Code": "FR",
                    "Example URL (Period Specified)": "http://dataservices.imf.org/REST/SDMX_JSON.svc/CompactData/CPI/A.FR.PCPIO_SRP_IX?startPeriod=2021-01-01&endPeriod=2023-01-01",
                    "Example URL (Complete Period)": "http://dataservices.imf.org/REST/SDMX_JSON.svc/CompactData/CPI/A.FR.PCPIO_SRP_IX",
                    "Example URL Description": "Returns the Miscellaneous goods and services, Standard Reference Period indicator for France at A frequency."
                },
                "Percentage change": {
                    "Indicator Key": "PCPIO_PC_CP_A_PT",
                    "Indicator Name": "Miscellaneous goods and services, Percentage change, Previous year",
                    "Indicator Database": "CPI",
                    "Example Frequency": "A",
                    "Example Region": "France",
                    "Example Region Code": "FR",
                    "Example URL (Period Specified)": "http://dataservices.imf.org/REST/SDMX_JSON.svc/CompactData/CPI/A.FR.PCPIO_PC_CP_A_PT?startPeriod=2021-01-01&endPeriod=2023-01-01",
                    "Example URL (Complete Period)": "http://dataservices.imf.org/REST/SDMX_JSON.svc/CompactData/CPI/A.FR.PCPIO_PC_CP_A_PT",
                    "Example URL Description": "Returns the Miscellaneous goods and services, Percentage change, Previous year indicator for France at A frequency."
                }
            }
        }
    }
}